{"getting_started_install_on_linux.md":"a04bf120","resources_tool.md":"4d66006e","concepts_volume.md":"9d17cb17","concepts_image.md":"04752e00","resources_playlist.md":"bc4cc1c3","about.md":"c9aa27d5","examples_hello_world.md":"9e48e26b","getting_started_uninstall_from_linux.md":"ee301ead","concepts_registry.md":"299c663d","index.md":"c4f88778","concepts_image_vs_container.md":"25bb71c5","getting_started_overview.md":"a04bc252","concepts_container.md":"b56bebd4","examples_ubuntu.md":"cd2ee941"}
